scraipe_st/__init__.py
scraipe_st/app.py
scraipe_st/component_repo.py
scraipe_st/default_config.py
scraipe_st/experimental/__init__.py
scraipe_st/experimental/telegram_component_provider.py
scraipe_st/utils.py
scraipe_st-0.1.5.dist-info/LICENSE
scraipe_st-0.1.5.dist-info/METADATA
scraipe_st-0.1.5.dist-info/WHEEL
scraipe_st-0.1.5.dist-info/RECORD
